sklearn_utilities/__init__.py
sklearn_utilities/append_prediction_to_x.py
sklearn_utilities/append_x_prediction_to_x.py
sklearn_utilities/dataset.py
sklearn_utilities/drop_by_noise_prediction.py
sklearn_utilities/drop_missing_columns.py
sklearn_utilities/drop_missing_rows_y.py
sklearn_utilities/estimator_wrapper.py
sklearn_utilities/eval_set.py
sklearn_utilities/event.py
sklearn_utilities/id_transformer.py
sklearn_utilities/intersect.py
sklearn_utilities/pandas/__init__.py
sklearn_utilities/pandas/column_transformer_pandas.py
sklearn_utilities/pandas/dataframe_wrapper.py
sklearn_utilities/pandas/feature_union_pandas.py
sklearn_utilities/pandas/multioutput.py
sklearn_utilities/proba/__init__.py
sklearn_utilities/proba/compose_var.py
sklearn_utilities/proba/dummy_regressor.py
sklearn_utilities/proba/pipeline_var.py
sklearn_utilities/proba/standard_scaler_var.py
sklearn_utilities/proba/transformed_target_estimator.py
sklearn_utilities/py.typed
sklearn_utilities/recursive_fit_subtract_regressor.py
sklearn_utilities/reindex_missing_columns.py
sklearn_utilities/report_non_finite.py
sklearn_utilities/torch/__init__.py
sklearn_utilities/torch/pca.py
sklearn_utilities/torch/skorch/__init__.py
sklearn_utilities/torch/skorch/proba.py
sklearn_utilities/torch/skorch/reshaper.py
sklearn_utilities/types.py
sklearn_utilities/utils.py
sklearn_utilities-0.5.14.dist-info/LICENSE
sklearn_utilities-0.5.14.dist-info/METADATA
sklearn_utilities-0.5.14.dist-info/WHEEL
sklearn_utilities-0.5.14.dist-info/RECORD
