Metadata-Version: 2.3
Name: sklearn-utilities
Version: 0.5.14
Summary: Utilities for scikit-learn.
License: MIT
Author: 34j
Author-email: 34j.95a2p@simplelogin.com
Requires-Python: >=3.9,<3.13
Classifier: Development Status :: 2 - Pre-Alpha
Classifier: Intended Audience :: Developers
Classifier: License :: OSI Approved :: MIT License
Classifier: Natural Language :: English
Classifier: Operating System :: OS Independent
Classifier: Programming Language :: Python :: 3
Classifier: Programming Language :: Python :: 3.9
Classifier: Programming Language :: Python :: 3.10
Classifier: Programming Language :: Python :: 3.11
Classifier: Programming Language :: Python :: 3.12
Classifier: Topic :: Software Development :: Libraries
Requires-Dist: lightgbm (>=4.1.0,<5.0.0)
Requires-Dist: pandas (>=2.1.1,<3.0.0)
Requires-Dist: scikit-learn (>=1.3.1,<2.0.0)
Requires-Dist: tqdm-joblib (>=0.0.4,<0.0.5)
Requires-Dist: typing-extensions (>=4.8.0,<5.0.0)
Project-URL: Bug Tracker, https://github.com/34j/sklearn-utilities/issues
Project-URL: Changelog, https://github.com/34j/sklearn-utilities/blob/main/CHANGELOG.md
Project-URL: Documentation, https://sklearn-utilities.readthedocs.io
Project-URL: Repository, https://github.com/34j/sklearn-utilities
